formulaic/__init__.py
formulaic/admin.py
formulaic/apps.py
formulaic/auto_populate.py
formulaic/beanstalk_jobs.py
formulaic/csv_export.py
formulaic/exceptions.py
formulaic/fields.py
formulaic/forms.py
formulaic/models.py
formulaic/rules.py
formulaic/serializers.py
formulaic/settings.py
formulaic/signals.py
formulaic/urls.py
formulaic/utils.py
formulaic/validators.py
formulaic/views.py
formulaic/widgets.py
formulaic/migrations/0001_initial.py
formulaic/migrations/0002_add_default_to_field_enabled.py
formulaic/migrations/0003_auto_20201230_1406.py
formulaic/migrations/0004_submission_promo_source.py
formulaic/migrations/__init__.py
formulaic/static/admin/formulaic/css/edit_fields.css
formulaic/static/admin/formulaic/css/form.css
formulaic/static/admin/formulaic/ember-formulaic/.bowerrc
formulaic/static/admin/formulaic/ember-formulaic/.editorconfig
formulaic/static/admin/formulaic/ember-formulaic/.ember-cli
formulaic/static/admin/formulaic/ember-formulaic/.eslintrc.js
formulaic/static/admin/formulaic/ember-formulaic/.gitignore
formulaic/static/admin/formulaic/ember-formulaic/.nvmrc
formulaic/static/admin/formulaic/ember-formulaic/.travis.yml
formulaic/static/admin/formulaic/ember-formulaic/.watchmanconfig
formulaic/static/admin/formulaic/ember-formulaic/README.md
formulaic/static/admin/formulaic/ember-formulaic/bower.json
formulaic/static/admin/formulaic/ember-formulaic/ember-cli-build.js
formulaic/static/admin/formulaic/ember-formulaic/npm-shrinkwrap.json
formulaic/static/admin/formulaic/ember-formulaic/package.json
formulaic/static/admin/formulaic/ember-formulaic/testem.js
formulaic/static/admin/formulaic/ember-formulaic/app/app.js
formulaic/static/admin/formulaic/ember-formulaic/app/index.html
formulaic/static/admin/formulaic/ember-formulaic/app/resolver.js
formulaic/static/admin/formulaic/ember-formulaic/app/router.js
formulaic/static/admin/formulaic/ember-formulaic/app/adapters/application.js
formification-1.1.3.dist-info/LICENSE
formification-1.1.3.dist-info/METADATA
formification-1.1.3.dist-info/WHEEL
formification-1.1.3.dist-info/top_level.txt
formification-1.1.3.dist-info/RECORD
